LICENSE
README.md
pyproject.toml
setup.py
id_mava.egg-info/PKG-INFO
id_mava.egg-info/SOURCES.txt
id_mava.egg-info/dependency_links.txt
id_mava.egg-info/requires.txt
id_mava.egg-info/top_level.txt
mava/__init__.py
mava/_metadata.py
mava/core.py
mava/core_jax.py
mava/core_jax_test.py
mava/environment_loop.py
mava/specs.py
mava/types.py
mava/adders/__init__.py
mava/adders/base.py
mava/adders/reverb/__init__.py
mava/adders/reverb/base.py
mava/adders/reverb/episode.py
mava/adders/reverb/sequence.py
mava/adders/reverb/transition.py
mava/adders/reverb/utils.py
mava/components/__init__.py
mava/components/tf/__init__.py
mava/components/tf/architectures/__init__.py
mava/components/tf/architectures/base.py
mava/components/tf/architectures/centralised.py
mava/components/tf/architectures/decentralised.py
mava/components/tf/architectures/networked.py
mava/components/tf/architectures/state_based.py
mava/components/tf/architectures/utils.py
mava/components/tf/losses/__init__.py
mava/components/tf/losses/sequence.py
mava/components/tf/modules/__init__.py
mava/components/tf/modules/communication/__init__.py
mava/components/tf/modules/communication/base.py
mava/components/tf/modules/communication/broadcasted.py
mava/components/tf/modules/exploration/__init__.py
mava/components/tf/modules/exploration/exploration_scheduling.py
mava/components/tf/modules/mixing/__init__.py
mava/components/tf/modules/mixing/mixers.py
mava/components/tf/modules/stabilising/__init__.py
mava/components/tf/modules/stabilising/fingerprints.py
mava/components/tf/networks/__init__.py
mava/components/tf/networks/communication.py
mava/components/tf/networks/continuous.py
mava/components/tf/networks/convolution.py
mava/components/tf/networks/distributional.py
mava/components/tf/networks/epsilon_greedy.py
mava/components/tf/networks/mad4pg.py
mava/environment_loops/__init__.py
mava/environment_loops/debugging_envs.py
mava/environment_loops/open_spiel_environment_loop.py
mava/systems/__init__.py
mava/systems/jax/__init__.py
mava/systems/jax/builder.py
mava/systems/jax/config.py
mava/systems/jax/config_test.py
mava/systems/jax/system.py
mava/systems/jax/system_test.py
